{"version":1,"resource":"file:///home/vugia/scripts/weekly_maintain.sh","entries":[{"id":"kX1x.sh","timestamp":1716258533474},{"id":"u78N.sh","timestamp":1716258607934},{"id":"q3QL.sh","timestamp":1716258635701},{"id":"0uta.sh","timestamp":1716259613370},{"id":"qn1j.sh","timestamp":1716259712092},{"id":"8Xh4.sh","timestamp":1716259950305},{"id":"V5h4.sh","timestamp":1716260015155},{"id":"aawc.sh","timestamp":1716260748408},{"id":"U9Vq.sh","timestamp":1716261100301},{"id":"mWYz.sh","timestamp":1716262436302},{"id":"IwK7.sh","timestamp":1716262500936},{"id":"e0bm.sh","timestamp":1716264508165},{"id":"meS0.sh","timestamp":1716264555006},{"id":"yILU.sh","timestamp":1743217966253},{"id":"5DZW.sh","timestamp":1743325730773}]}